<shape>
    <connections>
        <constraint x="0.5" y="0.075" perimeter="0" name="N"/>
        <constraint x="0.5" y="1" perimeter="0" name="S"/>
        <constraint x="0" y="0.39" perimeter="0" name="W"/>
        <constraint x="1" y="0.39" perimeter="0" name="E"/>
        <constraint x="0.165" y="0" perimeter="0" name="NW"/>
        <constraint x="0.115" y="0.87" perimeter="0" name="SW"/>
        <constraint x="0.835" y="0" perimeter="0" name="NE"/>
        <constraint x="0.885" y="0.87" perimeter="0" name="SE"/>
    </connections>
</shape>